{"Q_ID": "1211110015", "S_NAME": "Input and Output", "Q_NAME": "Display values", "Q_DESC": "Sita is awarded for scoring first mark in her 10th exams. To encourage her and other students, the school management has decided to display her mark sheet. \n\nDisplay her marks to the corresponding subjects.", "TESTCASE_1": "99 98 100 99 98\n###---###SEPERATOR---###---\n99\n98\n100\n99\n98", "TESTCASE_2": "12 13 14 15 16\n###---###SEPERATOR---###---\n12\n13\n14\n15\n16", "TESTCASE_3": "0\n###---###SEPERATOR---###---\n0", "TESTCASE_4": "0\n###---###SEPERATOR---###---\n0", "TESTCASE_5": "0\n###---###SEPERATOR---###---\n0"}