{"Q_ID": "1211310008", "S_NAME": "Input and Output", "Q_NAME": "Super Number", "Q_DESC": "Euler's phi function for a positive integer N is usually denoted as (N) and defined as the number of positive integers less than or equal to N that are coprime with N. Let's call a positive integer N a super number if N can be divided by (N) without a remainder. \ne.g. 2 is a super number (since 2 mod (2) = 0), while 3 is not (since 3 mod (3) = 1). \nYou are given two positive integers L and R. Your task is to find count of super numbers in the range [L, R]. \nInput\nEach test case is described by a single line containing two positive integers L and R Output\nFor each test case, output a single line containing one integer: the number of super numbers in the range.\n", "TESTCASE_1": "2 3\n###---###SEPERATOR---###---\n1", "TESTCASE_2": "90 95\n###---###SEPERATOR---###---\n0", "TESTCASE_3": "12 21\n###---###SEPERATOR---###---\n3", "TESTCASE_4": "0\n###---###SEPERATOR---###---\n0", "TESTCASE_5": "0\n###---###SEPERATOR---###---\n0"}