{"Q_ID": "1215110051", "S_NAME": "Function & Overloading", "Q_NAME": "2D and 3D Space", "Q_DESC": "Write a Program to find the distance between two points in 2D and 3D space using function overloading.\nInput:\nFirst line contains Point 1(2D)\nSecond line contains Point 2(2D)\nThird line contains Point 1(3D)\nFourth line contains Point 2(3D)", "TESTCASE_1": "90 40\n60 30\n60 40 20\n70 30 40\n###---###SEPERATOR---###---\nDistance between P1 & P2 is=31.6228\nDistance between P1 & P2 is=24.4949", "TESTCASE_2": "60 30\n30 20\n90 40 60\n75 55 62\n###---###SEPERATOR---###---\nDistance between P1 & P2 is=31.6228\nDistance between P1 & P2 is=21.3073", "TESTCASE_3": "10 10\n10 10\n20 20 20\n10 10 10\n###---###SEPERATOR---###---\nDistance between P1 & P2 is=0\nDistance between P1 & P2 is=17.3205", "TESTCASE_4": "0\n###---###SEPERATOR---###---\n0", "TESTCASE_5": "0\n###---###SEPERATOR---###---\n0"}