{"Q_ID": "1216210031", "S_NAME": "Arrays", "Q_NAME": "chef and childhood friend", "Q_DESC": "After visiting a childhood friend, Chef wants to get back to his home. Friend lives at the first street, and Chef himself lives at the N-th (and the last) street. Their city is a bit special: you can move from the X-th street to the Y-th street if and only if 1 = Y - X = K, where K is the integer value that is given to you. Chef wants to get to home in such a way that the product of all the visited streets' special numbers is minimal (including the first and the N-th street). Please, help him to find such a product.", "TESTCASE_1": "4 2\n1 2 3 4\n###---###SEPERATOR---###---\n8", "TESTCASE_2": "4 2\n1 2 3 7\n###---###SEPERATOR---###---\n14", "TESTCASE_3": "4 2\n11  2 13 7\n###---###SEPERATOR---###---\n154", "TESTCASE_4": "0\n###---###SEPERATOR---###---\n0", "TESTCASE_5": "0\n###---###SEPERATOR---###---\n0"}