{"Q_ID": "1218110032", "S_NAME": "Inheritance", "Q_NAME": "Find Largest value", "Q_DESC": "Program to display largest among two numbers using function templates.", "TESTCASE_1": "4\n5\n2.5\n3.2\na\nd\n###---###SEPERATOR---###---\n5 is larger.\n3.2 is larger.\nd has larger ASCII value.", "TESTCASE_2": "6\n8\n3.6\n2.1\nh\na\n###---###SEPERATOR---###---\n8 is larger.\n3.6 is larger.\nh has larger ASCII value.", "TESTCASE_3": "0\n###---###SEPERATOR---###---\n0", "TESTCASE_4": "0\n###---###SEPERATOR---###---\n0", "TESTCASE_5": "0\n###---###SEPERATOR---###---\n0"}