{"Q_ID": "1516110006", "S_NAME": "Page Replacement", "Q_NAME": "FIFO", "Q_DESC": "Write a program to implement First In First Out.FIFO Page Replacement technique is one of the simplest one to implement amongst other page replacement algorithms. It is a conservative algorithm.\n\nIt is a low-overhead algorithm that maintains a queue to keep a track of all the pages in a memory.\n\nWhen a page needs to be replaced, the page at the FRONT of the Queue will be replaced.\n\nInput:\n4\n6\n5 6 4 1 2 3\n\n4 = No of Frames\n6 = No of Pages\nFollowed by Pages\n", "TESTCASE_1": "4\n6\n5 6 4 1 2 3\n###---###SEPERATOR---###---\nFaults=6", "TESTCASE_2": "3\n5 \n4 1 2 4 5\n###---###SEPERATOR---###---\nFaults=4", "TESTCASE_3": "3\n5\n1 3 2 1 3\n###---###SEPERATOR---###---\nFaults=3", "TESTCASE_4": "0\n###---###SEPERATOR---###---\n0", "TESTCASE_5": "0\n###---###SEPERATOR---###---\n0"}