{"Q_ID": "1314110027", "S_NAME": "Arrays", "Q_NAME": "Distinct absolute array elements", "Q_DESC": "Count the number of distinct absolute values from a sorted array containing N integers. An absolute value of a number is | a |  ( positive ) value of it.\n \nInput\nThe first line of input contains an integer T denoting the number of test cases. Then T test cases follow. \nThe first line of each test case contains an integer N, where N is the size of the array A[ ].\nThe second line of each test case contains N space separated sorted integers, denoting elements of the array A[ ].\n\nNote: The array can contain duplicate values.\n \n\nOutput:\nFor each test case output a single line containing the no of distinct absolute values present in the array .\nRemember to output the answer of each test case in a new line.\n \n\nConstraints:\n1 = T = 100\n1 = N = 30\n-10^9= A[i] = 3*10^9", "TESTCASE_1": "3\n4\n-35 73 73 73 \n9\n-44 -31 -6 6 46 52 52 55 93\n6\n-3 -2 0 3 4 5\n###---###SEPERATOR---###---\n2\n7\n5", "TESTCASE_2": "5\n7\n1 5 78 34 22 19 56\n3\n65 243 21\n4\n12 34 56 78\n5\n19 28 38 47 58\n6\n12 98 34 87 45 76\n###---###SEPERATOR---###---\n7\n3\n4\n5\n6", "TESTCASE_3": "4\n5\n1 1 8 6 8\n6\n1 3 4 3 2 1\n7\n2 2 6 7 3 2 1\n4\n22 33 55 22\n###---###SEPERATOR---###---\n3\n4\n5\n3", "TESTCASE_4": "3\n3\n22 67 12\n6\n11 22 11 33 56 22\n5\n11 45 22 11 45\n###---###SEPERATOR---###---\n3\n4\n3", "TESTCASE_5": "0\n###---###SEPERATOR---###---\n0"}