{"Q_ID": "1317110057", "S_NAME": "Exception Handling and Th", "Q_NAME": "Simple Calculator", "Q_DESC": "Write a Java program to create a simple calculator. The program reads two numbers followed by an operator. Output of the program should be the result of the operation.\n\nAlso you need to handle NumberFormatException which arises when an invalid number is given as input. See examples for more details.\n", "TESTCASE_1": "4 5 -\n###---###SEPERATOR---###---\n-1", "TESTCASE_2": "4 4 +\n###---###SEPERATOR---###---\n8", "TESTCASE_3": "4 2 *\n###---###SEPERATOR---###---\n8", "TESTCASE_4": "4 2 /\n###---###SEPERATOR---###---\n2", "TESTCASE_5": "0\n###---###SEPERATOR---###---\n0"}