{"Q_ID": "1317310009", "S_NAME": "Strings", "Q_NAME": "STRING", "Q_DESC": "Given a string, add the length of each adjacent substring until it is reduced to a single number. \nInput Format:\nFirst line consists of a string\nOutput Format:\nResult after adding the length of each adjacent substring . Explanation:\nFor  the string A good beginning, the length is calculated as,\nA=1\nGood=4\nBeginning= 9\n1+4+9=14\n1+4=5", "TESTCASE_1": "twin peaks series\n###---###SEPERATOR---###---\n6", "TESTCASE_2": "face like a bull dog\n###---###SEPERATOR---###---\n7", "TESTCASE_3": "Phoenix market city\n###---###SEPERATOR---###---\n8", "TESTCASE_4": "0\n###---###SEPERATOR---###---\n0", "TESTCASE_5": "0\n###---###SEPERATOR---###---\n0"}