{"Q_ID": "1319310005", "S_NAME": "Exceptional Handling", "Q_NAME": "Chef and vectors", "Q_DESC": "Chef has an integer array X, and a binary array S, both of size N. He wants to know how many vectors (denote by V) of N elements exist, for which the following conditions hold for all valid indices i (that is, for all 1  i  N).\n\n0  Vi < 1018\nIf Si = 1, Vi is  Xi, and if Si = 0, Vi  Xi\nSum of the elements of V, when viewed as a string, contains \"47\" as a substring.\nPlease help Chef find this count. Since it may be a very large number, you should output the count modulo 109+7.", "TESTCASE_1": "2\n0 22\n0 30\n###---###SEPERATOR---###---\n6", "TESTCASE_2": "6\n0 55\n0 33\n0 22\n0 11\n0 56\n0 88\n###---###SEPERATOR---###---\n27547807", "TESTCASE_3": "0\n###---###SEPERATOR---###---\n0", "TESTCASE_4": "0\n###---###SEPERATOR---###---\n0", "TESTCASE_5": "0\n###---###SEPERATOR---###---\n0"}