{"Q_ID": "1111110056", "S_NAME": "Input & Ouput", "Q_NAME": "Big ", "Q_DESC": "Malu and Doss have play game.The condition to this game is both have to collect bangles from bowl one by one at a given time. Finally the judge have to decide who is the winner based on the count.", "TESTCASE_1": "10\n5\n###---###SEPERATOR---###---\n10", "TESTCASE_2": "4\n7\n###---###SEPERATOR---###---\n7", "TESTCASE_3": "89\n66\n###---###SEPERATOR---###---\n89", "TESTCASE_4": "0\n###---###SEPERATOR---###---\n0", "TESTCASE_5": "0 ###---###SEPERATOR---###--- 0"}