{"Q_ID": "1112110026", "S_NAME": "Data types", "Q_NAME": "Float Division of numbers", "Q_DESC": "Harinis home work for fourth day is to divide two numbers, help Harini to solve the problem.", "TESTCASE_1": "7.2 3.4\n###---###SEPERATOR---###---\nThe Division of two number is:2.117647", "TESTCASE_2": "1.8 7.2\n###---###SEPERATOR---###---\nThe Division of two number is:0.250000", "TESTCASE_3": "0\n###---###SEPERATOR---###---\n0", "TESTCASE_4": "0\n###---###SEPERATOR---###---\n0", "TESTCASE_5": "0 ###---###SEPERATOR---###--- 0"}