{"Q_ID": "1114210038", "S_NAME": "Control and Looping", "Q_NAME": "Pattern 15", "Q_DESC": "Write a program to print the given pattern.\n \nInput Format:\nInput consists of a single integer.\n \nOutput Format:\nRefer sample output. There is a trailing space at the end of each line.\n \nSample Input:\n5\n \nSample Output:\n5 5 5 5 5\n4 5 5 5 5\n3 4 5 5 5\n2 3 4 5 5\n1 2 3 4 5\n\n\n", "TESTCASE_1": "5\n###---###SEPERATOR---###---\n5 5 5 5 5 \n4 5 5 5 5 \n3 4 5 5 5 \n2 3 4 5 5 \n1 2 3 4 5", "TESTCASE_2": "9\n###---###SEPERATOR---###---\n9 9 9 9 9 9 9 9 9 \n8 9 9 9 9 9 9 9 9 \n7 8 9 9 9 9 9 9 9 \n6 7 8 9 9 9 9 9 9 \n5 6 7 8 9 9 9 9 9 \n4 5 6 7 8 9 9 9 9 \n3 4 5 6 7 8 9 9 9 \n2 3 4 5 6 7 8 9 9 \n1 2 3 4 5 6 7 8 9", "TESTCASE_3": "0\n###---###SEPERATOR---###---\n0", "TESTCASE_4": "0\n###---###SEPERATOR---###---\n0", "TESTCASE_5": "0 ###---###SEPERATOR---###--- 0"}