{"Q_ID": "1118210028", "S_NAME": "Structures and Unions", "Q_NAME": "Welcome message", "Q_DESC": "Ganapathy designed one system to display\nwelcome with his friends name, whatever name he says\nthe system reply welcome friend name. Solve this\nwith C structure code.\n\nInput Method\n\nName as Character of size 1 to 100\n\nOutput Method\n\nWelcome Name\n", "TESTCASE_1": "CSE\n###---###SEPERATOR---###---\nWelcome CSE", "TESTCASE_2": "ecE\n###---###SEPERATOR---###---\nWelcome ecE", "TESTCASE_3": "mEcH\n###---###SEPERATOR---###---\nWelcome mEcH", "TESTCASE_4": "0\n###---###SEPERATOR---###---\n0", "TESTCASE_5": "0 ###---###SEPERATOR---###--- 0"}