{"Q_ID": "1118110011", "S_NAME": "Structures and Unions", "Q_NAME": "Structure 42", "Q_DESC": "Write a program , using a pointer to a structure to initialize the members of the structure to display the students course registration details where details of first student initialized in the program and details of second student get from the user , then display the details of both student 1 and student 2\n\nInput and Output Format:\n\nRefer sample input and output for formatting specification.\n\nAll float values are displayed correct to 2 decimal places.\n\nAll text in bold corresponds to input and the rest corresponds to output.\n\nNote:\n\nUse structure and union concepts\n", "TESTCASE_1": "12 ram it 2333\n###---###SEPERATOR---###---\n\nRoll no:12\nName:ram\nCourse:it\nFees:2333", "TESTCASE_2": "15 john cse 15000\n###---###SEPERATOR---###---\nRoll no:15\nName:john\nCourse:cse\nFees:15000", "TESTCASE_3": "0\n###---###SEPERATOR---###---\n0", "TESTCASE_4": "0\n###---###SEPERATOR---###---\n0", "TESTCASE_5": "struct\n###---###SEPERATOR---###---\n0"}