{"Q_ID": "1119210031", "S_NAME": "Pointers", "Q_NAME": "Small Factorial", "Q_DESC": "All submissions for this problem are available.\n\nWrite a program to find the factorial value of any number entered by the user.\nInput\n\nThe first line contains an integer T, total number of testcases. Then follow T lines, each line contains an integer N.\nOutput\n\nDisplay the factorial of the given number N .\nConstraints\n\n    1  T  1000\n    0  N  20\n", "TESTCASE_1": "3\n3\n4\n5\n###---###SEPERATOR---###---\n6\n24\n120", "TESTCASE_2": "1\n4\n###---###SEPERATOR---###---\n24", "TESTCASE_3": "1\n5\n###---###SEPERATOR---###---\n120", "TESTCASE_4": "0\n###---###SEPERATOR---###---\n0", "TESTCASE_5": "0 ###---###SEPERATOR---###--- 0"}