{"Q_ID": "1614310004", "S_NAME": "Greedy Algorithm", "Q_NAME": "Sherlock and MiniMax", "Q_DESC": "Watson gives Sherlock an array A1,A2...AN. \nHe asks him to find an integer M between P and Q(both inclusive), such that, min {|Ai-M|, 1  i  N} is maximised. If there are multiple solutions, print the smallest one.\n\nSolution: M will be either A or B or (A_i+A_j)/2. We check for each pair and store if the answer is minimum.", "TESTCASE_1": "3\n5 8 14\n4 9\n###---###SEPERATOR---###---\n4", "TESTCASE_2": "2\n4 8 14\n4 2\n###---###SEPERATOR---###---\n4", "TESTCASE_3": "0\n###---###SEPERATOR---###---\n0", "TESTCASE_4": "0\n###---###SEPERATOR---###---\n0", "TESTCASE_5": "0\n###---###SEPERATOR---###---\n0"}