{"Q_ID": "1616110024", "S_NAME": "Backtracking", "Q_NAME": "Alphabets 1", "Q_DESC": "Given  alphabets x,y &z .Write a C Program to Generate All Permutations  of the  given alphabets using BackTracking", "TESTCASE_1": "xyz\n###---###SEPERATOR---###---\nxyz\nxzy\nyxz\nyzx\nzyx\nzxy", "TESTCASE_2": "yxz\n###---###SEPERATOR---###---\nyxz\nyzx\nxyz\nxzy\nzxy\nzyx", "TESTCASE_3": "wrty\n###---###SEPERATOR---###---\nwrty\nwryt\nwtry\nwtyr\nwytr\nwyrt\nrwty\nrwyt\nrtwy\nrtyw\nrytw\nrywt\ntrwy\ntryw\ntwry\ntwyr\ntywr\ntyrw\nyrtw\nyrwt\nytrw\nytwr\nywtr\nywrt", "TESTCASE_4": "zerty\n###---###SEPERATOR---###---\nzerty\nzeryt\nzetry\nzetyr\nzeytr\nzeyrt\nzrety\nzreyt\nzrtey\nzrtye\nzryte\nzryet\nztrey\nztrye\nztery\nzteyr\nztyer\nztyre\nzyrte\nzyret\nzytre\nzyter\nzyetr\nzyert\nezrty\nezryt\neztry\neztyr\nezytr\nezyrt\nerzty\nerzyt\nertzy\nertyz\nerytz\neryzt\netrzy\netryz\netzry\netzyr\netyzr\netyrz\neyrtz\neyrzt\neytrz\neytzr\neyztr\neyzrt\nrezty\nrezyt\nretzy\nretyz\nreytz\nreyzt\nrzety\nrzeyt\nrztey\nrztye\nrzyte\nrzyet\nrtzey\nrtzye\nrtezy\nrteyz\nrtyez\nrtyze\nryzte\nryzet\nrytze\nrytez\nryetz\nryezt\nterzy\nteryz\ntezry\ntezyr\nteyzr\nteyrz\ntrezy\ntreyz\ntrzey\ntrzye\ntryze\ntryez\ntzrey\ntzrye\ntzery\ntzeyr\ntzyer\ntzyre\ntyrze\ntyrez\ntyzre\ntyzer\ntyezr\ntyerz\nyertz\nyerzt\nyetrz\nyetzr\nyeztr\nyezrt\nyretz\nyrezt\nyrtez\nyrtze\nyrzte\nyrzet\nytrez\nytrze\nyterz\nytezr\nytzer\nytzre\nyzrte\nyzret\nyztre\nyzter\nyzetr\nyzert", "TESTCASE_5": "0\n###---###SEPERATOR---###---\n0"}