{"Q_ID": "1619310005", "S_NAME": "Sum of Subsets", "Q_NAME": "Subset Sum Problem", "Q_DESC": "Objective: Given a set of positive integers, and a value sum S, find out if there exist a subset in array whose sum is equal to given sum S.\n\nExample:\n\nint[] A = { 3, 2, 7, 1}, S = 6\n\nOutput: True, subset is (3, 2, 1}     Input Format:                                   First line- is the no:of elements in the set.                                                 Then enter the elements in the set                                                     Last line is the sum", "TESTCASE_1": "6\n3\n34\n4\n12\n5\n2\n9\n###---###SEPERATOR---###---\nFound a subset with given sum", "TESTCASE_2": "4\n2\n3\n1\n6\n15\n###---###SEPERATOR---###---\nNo subset with given sum", "TESTCASE_3": "0\n###---###SEPERATOR---###---\n0", "TESTCASE_4": "0\n###---###SEPERATOR---###---\n0", "TESTCASE_5": "0\n###---###SEPERATOR---###---\n0"}