{"Q_ID": "1412110013", "S_NAME": "Arrays", "Q_NAME": "Stock buy and sell", "Q_DESC": "The cost of a stock on each day is given in an array, find the max profit that you can make by buying and selling in those days. \n\nInput:\nFirst line contains number of test cases T. Each test case contain the integer value N denoting days followed by an array of stock prices in N days.\nOutput:\nThe maximum profit is displayed as shown below. And if there is no profit then print No Profit.\n\n\nConstraints:\n1 =T=100\n2 =N=100\n1 =arr[i]=10000", "TESTCASE_1": "2\n7\n100 180 260 310 40 535 695\n10\n23 13 25 29 33 19 34 45 65 67\n###---###SEPERATOR---###---\n(0 3) (4 6)\n(1 4) (5 9)", "TESTCASE_2": "2\n5\n10 80 60 30 40 53 65\n10\n2 1 5 9 3 8 4 5 6 7\n###---###SEPERATOR---###---\n(0 1) (3 4)\n(3 5) (6 7) (8 11) (12 13) (14 15) (16 17) (18 19) (20 21) (23 26)(30 31) (32 33) (36 37) (38 39) (40 41) (44 45) (46 47) (50 52)", "TESTCASE_3": "0\n###---###SEPERATOR---###---\n0", "TESTCASE_4": "0\n###---###SEPERATOR---###---\n0", "TESTCASE_5": "0\n###---###SEPERATOR---###---\n0"}