{"Q_ID": "1415210024", "S_NAME": "Linked List Implementatio", "Q_NAME": "Linked List 52", "Q_DESC": "To write a program in which the user has to perform operations in a linked list.\nUnion and Intersection of two Linked Lists. The task is to make two Linked Lists, create union and intersection lists that contain union and intersection of the elements present in the given lists.\n\nINPUT:\n10 15 5 2 // linked list 2\n 8 4 2 10//linked list 2\nOUTPUT:\nFirst list is \n2 5 15 10 \nSecond list is \n10 2 4 8 \nIntersection list is \n10 2 \nUnion list is \n8 4 10 15 5 2\n", "TESTCASE_1": "10 15 5 2 8 4 2 10\n###---###SEPERATOR---###---\nFirst list is \n2 5 15 10 \nSecond list is \n10 2 4 8 \nIntersection list is \n10 2 \nUnion list is \n8 4 10 15 5 2", "TESTCASE_2": "1 2 3 4 5 4 3 2 \n###---###SEPERATOR---###---\nFirst list is \n4 3 2 1 \nSecond list is \n2 3 4 5 \nIntersection list is \n2 3 4 \nUnion list is \n5 1 2 3 4", "TESTCASE_3": "78 65 34 90 90 4 3 2\n\n###---###SEPERATOR---###---\nFirst list is \n90 34 65 78 \nSecond list is \n2 3 4 90 \nIntersection list is \n90 \nUnion list is \n4 3 2 78 65 34 90", "TESTCASE_4": "0\n###---###SEPERATOR---###---\n0", "TESTCASE_5": "0\n###---###SEPERATOR---###---\n0"}