{"Q_ID": "1415310009", "S_NAME": "Linked List  Implementati", "Q_NAME": "Linked List 29", "Q_DESC": "To write a program in which the user has to input number of elements and enter elements into a singly linked list.\nNow the user has to input two integers M and N. Traverse the linked list such that you retain M nodes then delete next N nodes, continue the same till end of the linked list.\nINPUT:\n7 //number of elements\n11 //first element\n22 //second element\n33 //third element\n44 //fourth element\n55 //fifth element\n66 //sixth element\n77 //seventh element\n2 //M\n2 //N\nOUTPUT:\nM = 2, N = 1 \nGiven Linked list is :\n77 66 55 44 33 22 11 \n\nLinked list after deletion is :\n77 66 44 33 11 ", "TESTCASE_1": "7 11 22 33 44 55 66 77 2 1\n###---###SEPERATOR---###---\nM = 2, N = 1 \nGiven Linked list is :\n77 66 55 44 33 22 11 \n\nLinked list after deletion is :\n77 66 44 33 11 ", "TESTCASE_2": "10 69 98 43 11 22 33 44 55 66 77 2 2\n###---###SEPERATOR---###---\nM = 2, N = 2 \nGiven Linked list is :\n77 66 55 44 33 22 11 43 98 69 \n\nLinked list after deletion is :\n77 66 33 22 98 69 0", "TESTCASE_3": "14 23 45 67 46 69 98 43 11 22 33 44 55 66 77 2 3\n###---###SEPERATOR---###---\nM = 2, N = 3 \nGiven Linked list is :\n77 66 55 44 33 22 11 43 98 69 46 67 45 23 \n\nLinked list after deletion is :\n77 66 22 11 46 67", "TESTCASE_4": "0\n###---###SEPERATOR---###---\n0", "TESTCASE_5": "0\n###---###SEPERATOR---###---\n0"}