{"Q_ID": "1416110017", "S_NAME": "Stack Implementation", "Q_NAME": "Stack 16", "Q_DESC": "Find maximum sum possible equal sum of three stacks\nGiven three stack of the positive numbers, the task is to find the possible equal maximum sum of the stacks with removal of top elements allowed. Stacks are represented as array, and the first index of the array represent the top element of the stack.\n\nINPUT:\nfirst line of input must contain size of stack1\nsecond line of input must contain size of stack2\nthird line of input must contain size of stack3\nfourth line of input must contain all elements to be pushed into stack1\nfifth line of input must contain all elements to be pushed into stack2\nsixth line of input must contain all elements to be pushed into stack3", "TESTCASE_1": "5\n3\n4\n3 2 1 1 1\n4 3 2\n1 1 4 1\n###---###SEPERATOR---###---\n5", "TESTCASE_2": "2\n2\n2\n3 10\n4 5 \n2 1\n###---###SEPERATOR---###---\n0", "TESTCASE_3": "0\n###---###SEPERATOR---###---\n0", "TESTCASE_4": "0\n###---###SEPERATOR---###---\n0", "TESTCASE_5": "0\n###---###SEPERATOR---###---\n0"}