{"Q_ID": "1416110112", "S_NAME": "Stack", "Q_NAME": "Evaluate Postfix", "Q_DESC": "Using Stack evaluate postfix expression\n\nINPUT\nFirst line contains the postfix expression\nOUTPUT\nThe value of postfix expression", "TESTCASE_1": "231*+9-\n###---###SEPERATOR---###---\nValue of 231*+9- is -4", "TESTCASE_2": "123*+98\n###---###SEPERATOR---###---\nValue of 123*+98 is 8", "TESTCASE_3": "231/+9*\n###---###SEPERATOR---###---\nValue of 231/+9* is 45", "TESTCASE_4": "0\n###---###SEPERATOR---###---\n0", "TESTCASE_5": "0\n###---###SEPERATOR---###---\n0"}