{"Q_ID": "1418310011", "S_NAME": "Tree", "Q_NAME": "Number of leaf nodes ", "Q_DESC": "Make a tree and print the number of nodes.\n\nThe first line of input contains a variable 'T'. Next 'T' lines contain the values of tree nodes. \n\nOutput contains the number of leaf nodes of the tree", "TESTCASE_1": "11\n12\n5\n21\n4\n8\n28\n2\n6\n7\n23\n25\n###---###SEPERATOR---###---\nHow many numbers do you want to insert ?\nTotal number of leaf nodes: 3", "TESTCASE_2": "0\n###---###SEPERATOR---###---\n0", "TESTCASE_3": "0\n###---###SEPERATOR---###---\n0", "TESTCASE_4": "0\n###---###SEPERATOR---###---\n0", "TESTCASE_5": "0\n###---###SEPERATOR---###---\n0"}